toumoro_cdk/cognito/__init__.py
toumoro_cdk/cognito/py.typed
toumoro_cdk/cognito/_jsii/__init__.py
toumoro_cdk/cognito/_jsii/cognito@1.1.0.jsii.tgz
toumoro_cdk.cognito-1.1.0.dist-info/LICENSE
toumoro_cdk.cognito-1.1.0.dist-info/METADATA
toumoro_cdk.cognito-1.1.0.dist-info/WHEEL
toumoro_cdk.cognito-1.1.0.dist-info/top_level.txt
toumoro_cdk.cognito-1.1.0.dist-info/RECORD
