Metadata-Version: 2.1
Name: toumoro-cdk.cognito
Version: 1.1.0
Summary: Creates a cognito userpool and app client
Home-page: https://github.com/toumoro/toumoro-cdk.git
Author: Your name<Your email address>
License: Apache-2.0
Project-URL: Source, https://github.com/toumoro/toumoro-cdk.git
Platform: UNKNOWN
Classifier: Intended Audience :: Developers
Classifier: Operating System :: OS Independent
Classifier: Programming Language :: JavaScript
Classifier: Programming Language :: Python :: 3 :: Only
Classifier: Programming Language :: Python :: 3.7
Classifier: Programming Language :: Python :: 3.8
Classifier: Programming Language :: Python :: 3.9
Classifier: Programming Language :: Python :: 3.10
Classifier: Typing :: Typed
Classifier: License :: OSI Approved
Requires-Python: ~=3.7
License-File: LICENSE
Requires-Dist: aws-cdk-lib (<3.0.0,>=2.25.0)
Requires-Dist: constructs (<11.0.0,>=10.1.22)
Requires-Dist: jsii (<2.0.0,>=1.59.0)
Requires-Dist: publication (>=0.0.3)
